tools_sushi/__init__.py
tools_sushi/bundle.py
tools_sushi/main.py
tools_sushi/api/__init__.py
tools_sushi/api/file.py
tools_sushi/api/network/__init__.py
tools_sushi/api/network/http_server.py
tools_sushi/api/subclass/__init__.py
tools_sushi/api/subclass/app.py
tools_sushi/api/subclass/http.py
tools_sushi/api/terminal/__init__.py
tools_sushi/api/terminal/colors.py
tools_sushi/api/terminal/input.py
tools_sushi/config/__init__.py
tools_sushi/config/reader.py
tools_sushi/exceptions/ConfigNotFound.py
tools_sushi/exceptions/__init__.py
tools_sushi-0.0.28a0.dist-info/LICENSE
tools_sushi-0.0.28a0.dist-info/METADATA
tools_sushi-0.0.28a0.dist-info/WHEEL
tools_sushi-0.0.28a0.dist-info/entry_points.txt
tools_sushi-0.0.28a0.dist-info/top_level.txt
tools_sushi-0.0.28a0.dist-info/RECORD
