Metadata-Version: 2.1
Name: tools-sushi
Version: 0.0.28a0
Summary: create applications faster than ever
Home-page: https://github.com/sushi-tools/sushi
Author: ksawery29
Author-email: sushicontact1@gmail.com
License-File: LICENSE
